LICENSE
README.md
setup.py
baselib/__init__.py
baselib.egg-info/PKG-INFO
baselib.egg-info/SOURCES.txt
baselib.egg-info/dependency_links.txt
baselib.egg-info/not-zip-safe
baselib.egg-info/top_level.txt
baselib/channel/__init__.py
baselib/channel/base_channel.py
baselib/demo/__init__.py
baselib/demo/demo.py
baselib/feishu/__init__.py
baselib/feishu/robot.py
baselib/json/__init__.py
baselib/json/json_file.py
baselib/log/__init__.py
baselib/log/file.py
baselib/py/__init__.py
baselib/qywx/__init__.py
baselib/qywx/qywx.py
baselib/request/__init__.py
baselib/system/__init__.py
baselib/tests/__init__.py
baselib/tests/debug.py
baselib/tests/demo_test.py
baselib/tests/file_logger_test.py
baselib/tests/httplib_test.py
baselib/tests/json_file_test.py
baselib/tests/period_test.py
baselib/tests/qywx_test.py
baselib/time/__init__.py
baselib/time/period.py