Metadata-Version: 2.1
Name: baselib
Version: 1.1.0.2
Summary: base common lib for python
Home-page: https://github.com/coreylam/base_common_lib
Author: coreylam
Author-email: coreylam@163.com
License: GPL
Requires-Python: >=2.7
License-File: LICENSE
